LICENSE.txt
MANIFEST.in
README.txt
fen.py
setup.py
fen/__init__.py
fen.egg-info/PKG-INFO
fen.egg-info/SOURCES.txt
fen.egg-info/dependency_links.txt
fen.egg-info/requires.txt
fen.egg-info/top_level.txt
images/black_bishop.svg
images/black_king.svg
images/black_knight.svg
images/black_pawn.svg
images/black_queen.svg
images/black_rook.svg
images/white_bishop.svg
images/white_king.svg
images/white_knight.svg
images/white_pawn.svg
images/white_queen.svg
images/white_rook.svg